fdw/__main__.py
file_directory_watcher/app.py
file_directory_watcher/argument_parser.py
file_directory_watcher/cli.py
file_directory_watcher/const.py
file_directory_watcher/helpers.py
file_directory_watcher/utils.py
file_directory_watcher-0.0.10.dist-info/LICENSE
file_directory_watcher-0.0.10.dist-info/METADATA
file_directory_watcher-0.0.10.dist-info/WHEEL
file_directory_watcher-0.0.10.dist-info/entry_points.txt
file_directory_watcher-0.0.10.dist-info/top_level.txt
file_directory_watcher-0.0.10.dist-info/RECORD
